<?xml version="1.0" encoding="UTF-8"?>

<Parameters>
  <PARAM id="ATTACK_1" value="0.4609999656677246"/>
  <PARAM id="ATTACK_2" value="0.210999995470047"/>
  <PARAM id="ATTACK_3" value="0.1710000038146973"/>
  <PARAM id="ATTACK_4" value="0.5809999704360962"/>
  <PARAM id="ATTACK_5" value="0.1609999984502792"/>
  <PARAM id="ATTACK_6" value="0.8009999394416809"/>
  <PARAM id="AUDIO_ROUTE_0_0" value="0.0"/>
  <PARAM id="AUDIO_ROUTE_0_1" value="0.0"/>
  <PARAM id="AUDIO_ROUTE_0_2" value="0.8399999737739563"/>
  <PARAM id="AUDIO_ROUTE_0_3" value="0.2699999809265137"/>
  <PARAM id="AUDIO_ROUTE_0_4" value="0.0"/>
  <PARAM id="AUDIO_ROUTE_0_5" value="0.85999995470047"/>
  <PARAM id="AUDIO_ROUTE_1_0" value="0.0"/>
  <PARAM id="AUDIO_ROUTE_1_1" value="0.3400000035762787"/>
  <PARAM id="AUDIO_ROUTE_1_2" value="0.0"/>
  <PARAM id="AUDIO_ROUTE_1_3" value="0.0"/>
  <PARAM id="AUDIO_ROUTE_1_4" value="0.0"/>
  <PARAM id="AUDIO_ROUTE_1_5" value="0.7599999904632568"/>
  <PARAM id="AUDIO_ROUTE_2_0" value="1.0"/>
  <PARAM id="AUDIO_ROUTE_2_1" value="0.0"/>
  <PARAM id="AUDIO_ROUTE_2_2" value="0.1799999922513962"/>
  <PARAM id="AUDIO_ROUTE_2_3" value="0.0"/>
  <PARAM id="AUDIO_ROUTE_2_4" value="0.0"/>
  <PARAM id="AUDIO_ROUTE_2_5" value="0.3299999833106995"/>
  <PARAM id="AUDIO_ROUTE_3_0" value="0.0"/>
  <PARAM id="AUDIO_ROUTE_3_1" value="0.0"/>
  <PARAM id="AUDIO_ROUTE_3_2" value="0.2699999809265137"/>
  <PARAM id="AUDIO_ROUTE_3_3" value="0.8399999737739563"/>
  <PARAM id="AUDIO_ROUTE_3_4" value="0.0"/>
  <PARAM id="AUDIO_ROUTE_3_5" value="0.0"/>
  <PARAM id="AUDIO_ROUTE_4_0" value="0.0"/>
  <PARAM id="AUDIO_ROUTE_4_1" value="0.0"/>
  <PARAM id="AUDIO_ROUTE_4_2" value="0.0"/>
  <PARAM id="AUDIO_ROUTE_4_3" value="0.0"/>
  <PARAM id="AUDIO_ROUTE_4_4" value="0.4399999976158142"/>
  <PARAM id="AUDIO_ROUTE_4_5" value="0.1899999976158142"/>
  <PARAM id="AUDIO_ROUTE_5_0" value="0.0"/>
  <PARAM id="AUDIO_ROUTE_5_1" value="0.0"/>
  <PARAM id="AUDIO_ROUTE_5_2" value="0.6100000143051147"/>
  <PARAM id="AUDIO_ROUTE_5_3" value="0.09999999403953552"/>
  <PARAM id="AUDIO_ROUTE_5_4" value="0.0"/>
  <PARAM id="AUDIO_ROUTE_5_5" value="0.0"/>
  <PARAM id="DECAY_1" value="2.960000038146973"/>
  <PARAM id="DECAY_2" value="1.399999976158142"/>
  <PARAM id="DECAY_3" value="1.339999914169312"/>
  <PARAM id="DECAY_4" value="1.230000019073486"/>
  <PARAM id="DECAY_5" value="2.589999914169312"/>
  <PARAM id="DECAY_6" value="2.049999952316284"/>
  <PARAM id="DETUNE_1" value="-31.93000030517578"/>
  <PARAM id="DETUNE_2" value="37.72000122070312"/>
  <PARAM id="DETUNE_3" value="-42.27000045776367"/>
  <PARAM id="DETUNE_4" value="-48.7599983215332"/>
  <PARAM id="DETUNE_5" value="44.38999938964844"/>
  <PARAM id="DETUNE_6" value="6.909999847412109"/>
  <PARAM id="FILTER_TYPE_1" value="7.0"/>
  <PARAM id="FILTER_TYPE_2" value="18.0"/>
  <PARAM id="FILTER_TYPE_3" value="10.0"/>
  <PARAM id="FILTER_TYPE_4" value="17.0"/>
  <PARAM id="FILTER_TYPE_5" value="1.0"/>
  <PARAM id="FILTER_TYPE_6" value="0.0"/>
  <PARAM id="FOLD_1" value="0.199999988079071"/>
  <PARAM id="FOLD_2" value="0.4399999976158142"/>
  <PARAM id="FOLD_3" value="0.1899999976158142"/>
  <PARAM id="FOLD_4" value="0.02999999932944775"/>
  <PARAM id="FOLD_5" value="0.6399999856948853"/>
  <PARAM id="FOLD_6" value="0.8399999737739563"/>
  <PARAM id="FX_DETUNE_1" value="31.94999694824219"/>
  <PARAM id="FX_DETUNE_2" value="0.0"/>
  <PARAM id="FX_DETUNE_3" value="47.18999481201172"/>
  <PARAM id="FX_FOLD_1" value="0.1700000017881393"/>
  <PARAM id="FX_FOLD_2" value="0.3499999940395355"/>
  <PARAM id="FX_FOLD_3" value="0.5099999904632568"/>
  <PARAM id="FX_MIX_1" value="0.4099999964237213"/>
  <PARAM id="FX_MIX_2" value="1.0"/>
  <PARAM id="FX_MIX_3" value="0.0"/>
  <PARAM id="FX_PHASE_1" value="2.159999847412109"/>
  <PARAM id="FX_PHASE_2" value="0.0"/>
  <PARAM id="FX_PHASE_3" value="212.3499908447266"/>
  <PARAM id="FX_RATIO_1" value="1.360000014305115"/>
  <PARAM id="FX_RATIO_2" value="13.88000011444092"/>
  <PARAM id="FX_RATIO_3" value="8.560000419616699"/>
  <PARAM id="FX_SYNC_1" value="1.0"/>
  <PARAM id="FX_SYNC_2" value="0.0"/>
  <PARAM id="FX_SYNC_3" value="1.0"/>
  <PARAM id="FX_TYPE_1" value="2.0"/>
  <PARAM id="FX_TYPE_2" value="1.0"/>
  <PARAM id="FX_TYPE_3" value="5.0"/>
  <PARAM id="GAIN_CEIL" value="-4.399999618530273"/>
  <PARAM id="MODE_1" value="0.0"/>
  <PARAM id="MODE_2" value="1.0"/>
  <PARAM id="MODE_3" value="0.0"/>
  <PARAM id="MODE_4" value="0.0"/>
  <PARAM id="MODE_5" value="1.0"/>
  <PARAM id="MODE_6" value="0.0"/>
  <PARAM id="MOD_0_0" value="2.539999961853027"/>
  <PARAM id="MOD_0_1" value="0.0"/>
  <PARAM id="MOD_0_2" value="0.0"/>
  <PARAM id="MOD_0_3" value="0.0"/>
  <PARAM id="MOD_0_4" value="0.0"/>
  <PARAM id="MOD_0_5" value="0.0"/>
  <PARAM id="MOD_1_0" value="0.0"/>
  <PARAM id="MOD_1_1" value="0.0"/>
  <PARAM id="MOD_1_2" value="8.84999942779541"/>
  <PARAM id="MOD_1_3" value="0.0"/>
  <PARAM id="MOD_1_4" value="1.809999942779541"/>
  <PARAM id="MOD_1_5" value="0.0"/>
  <PARAM id="MOD_2_0" value="0.0"/>
  <PARAM id="MOD_2_1" value="0.0"/>
  <PARAM id="MOD_2_2" value="0.0"/>
  <PARAM id="MOD_2_3" value="0.0"/>
  <PARAM id="MOD_2_4" value="0.0"/>
  <PARAM id="MOD_2_5" value="0.0"/>
  <PARAM id="MOD_3_0" value="0.0"/>
  <PARAM id="MOD_3_1" value="0.0"/>
  <PARAM id="MOD_3_2" value="2.470000028610229"/>
  <PARAM id="MOD_3_3" value="0.0"/>
  <PARAM id="MOD_3_4" value="0.0"/>
  <PARAM id="MOD_3_5" value="0.0"/>
  <PARAM id="MOD_4_0" value="0.0"/>
  <PARAM id="MOD_4_1" value="7.199999809265137"/>
  <PARAM id="MOD_4_2" value="9.689999580383301"/>
  <PARAM id="MOD_4_3" value="8.590000152587891"/>
  <PARAM id="MOD_4_4" value="7.809999942779541"/>
  <PARAM id="MOD_4_5" value="0.0"/>
  <PARAM id="MOD_5_0" value="0.0"/>
  <PARAM id="MOD_5_1" value="0.0"/>
  <PARAM id="MOD_5_2" value="0.0"/>
  <PARAM id="MOD_5_3" value="8.179999351501465"/>
  <PARAM id="MOD_5_4" value="3.069999933242798"/>
  <PARAM id="MOD_5_5" value="1.819999933242798"/>
  <PARAM id="MOD_AMT_1" value="-1.0"/>
  <PARAM id="MOD_AMT_2" value="0.1499999761581421"/>
  <PARAM id="MOD_AMT_3" value="0.4299999475479126"/>
  <PARAM id="MOD_AMT_4" value="-1.0"/>
  <PARAM id="MOD_AMT_5" value="-1.0"/>
  <PARAM id="MOD_AMT_6" value="0.04999995231628418"/>
  <PARAM id="MOD_SRC_1" value="0.0"/>
  <PARAM id="MOD_SRC_2" value="0.0"/>
  <PARAM id="MOD_SRC_3" value="0.0"/>
  <PARAM id="MOD_SRC_4" value="5.0"/>
  <PARAM id="MOD_SRC_5" value="0.0"/>
  <PARAM id="MOD_SRC_6" value="3.0"/>
  <PARAM id="MOD_TGT_1" value="0.0"/>
  <PARAM id="MOD_TGT_2" value="16.0"/>
  <PARAM id="MOD_TGT_3" value="12.0"/>
  <PARAM id="MOD_TGT_4" value="0.0"/>
  <PARAM id="MOD_TGT_5" value="21.0"/>
  <PARAM id="MOD_TGT_6" value="0.0"/>
  <PARAM id="OUT_1" value="0.7199999690055847"/>
  <PARAM id="OUT_2" value="0.8299999833106995"/>
  <PARAM id="OUT_3" value="0.7199999690055847"/>
  <PARAM id="OUT_4" value="0.6399999856948853"/>
  <PARAM id="OUT_5" value="0.75"/>
  <PARAM id="OUT_6" value="0.7599999904632568"/>
  <PARAM id="PHASE_1" value="266.6199951171875"/>
  <PARAM id="PHASE_2" value="14.17999935150146"/>
  <PARAM id="PHASE_3" value="278.1300048828125"/>
  <PARAM id="PHASE_4" value="33.79999923706055"/>
  <PARAM id="PHASE_5" value="167.9199981689453"/>
  <PARAM id="PHASE_6" value="42.04999923706055"/>
  <PARAM id="RATIO_1" value="12.59000015258789"/>
  <PARAM id="RATIO_2" value="1.329999923706055"/>
  <PARAM id="RATIO_3" value="3.399999856948853"/>
  <PARAM id="RATIO_4" value="13.21000003814697"/>
  <PARAM id="RATIO_5" value="3.319999933242798"/>
  <PARAM id="RATIO_6" value="2.259999990463257"/>
  <PARAM id="RELEASE_1" value="2.779999971389771"/>
  <PARAM id="RELEASE_2" value="1.129999995231628"/>
  <PARAM id="RELEASE_3" value="2.259999990463257"/>
  <PARAM id="RELEASE_4" value="2.059999942779541"/>
  <PARAM id="RELEASE_5" value="2.369999885559082"/>
  <PARAM id="RELEASE_6" value="0.949999988079071"/>
  <PARAM id="SUSTAIN_1" value="0.2999999821186066"/>
  <PARAM id="SUSTAIN_2" value="0.7599999904632568"/>
  <PARAM id="SUSTAIN_3" value="0.3100000023841858"/>
  <PARAM id="SUSTAIN_4" value="0.8899999856948853"/>
  <PARAM id="SUSTAIN_5" value="0.6899999976158142"/>
  <PARAM id="SUSTAIN_6" value="0.8899999856948853"/>
  <PARAM id="TEMPO_SYNC_1" value="0.0"/>
  <PARAM id="TEMPO_SYNC_2" value="1.0"/>
  <PARAM id="TEMPO_SYNC_3" value="0.0"/>
  <PARAM id="TEMPO_SYNC_4" value="1.0"/>
  <PARAM id="TEMPO_SYNC_5" value="1.0"/>
  <PARAM id="TEMPO_SYNC_6" value="0.0"/>
  <PARAM id="WAVE_SHAPE_1" value="2.0"/>
  <PARAM id="WAVE_SHAPE_2" value="4.0"/>
  <PARAM id="WAVE_SHAPE_3" value="0.0"/>
  <PARAM id="WAVE_SHAPE_4" value="7.0"/>
  <PARAM id="WAVE_SHAPE_5" value="4.0"/>
  <PARAM id="WAVE_SHAPE_6" value="3.0"/>
</Parameters>
